pyorca/__init__.py
pyorca/const.py
pyorca/run.py
pyorca/settings.py
pyorca/input/__init__.py
pyorca/input/file.py
pyorca/input/block/__init__.py
pyorca/input/block/_base.py
pyorca/input/block/coords/__init__.py
pyorca/input/block/coords/_base.py
pyorca/output/__init__.py
pyorca/output/gbw.py
pyorca/output/main.py
pyorca/output/prop.py
orca_api-0.0.3.dist-info/METADATA
orca_api-0.0.3.dist-info/WHEEL
orca_api-0.0.3.dist-info/top_level.txt
orca_api-0.0.3.dist-info/RECORD
