Metadata-Version: 2.4
Name: ORCA-API
Version: 0.0.3
Requires-Python: >=3.10
Requires-Dist: matplotlib
Requires-Dist: numpy
Requires-Dist: pandas
Requires-Dist: pyshellman<0.3,>=0.2.1
Requires-Dist: SciCoDa<0.3,>=0.2.3
